fast_n-0.0.2.dist-info/licenses/LICENCE
fastn/noise.py
fastn/utilities.py
fast_n-0.0.2.dist-info/METADATA
fast_n-0.0.2.dist-info/WHEEL
fast_n-0.0.2.dist-info/top_level.txt
fast_n-0.0.2.dist-info/RECORD
