Metadata-Version: 2.4
Name: fast_n
Version: 0.0.2
Summary: A fast noise library for game dev.
Author-email: greenKac <greenkac.greener@gmail.com>
Project-URL: Homepage, https://github.com/greenKac/fast_n
Classifier: Programming Language :: Python :: 3.11
Classifier: License :: OSI Approved :: MIT License
Classifier: Operating System :: Microsoft :: Windows
Requires-Python: >=3.11
License-File: LICENCE
Dynamic: license-file
